pacer_tools/__init__.py
pacer_tools/code/__init__.py
pacer_tools/code/cli.py
pacer_tools/code/downloader/__init__.py
pacer_tools/code/downloader/forms.py
pacer_tools/code/downloader/scraper_tools.py
pacer_tools/code/downloader/scrapers.py
pacer_tools/code/downloader/tools.py
pacer_tools/code/parsers/__init__.py
pacer_tools/code/parsers/parse_pacer.py
pacer_tools/code/parsers/parse_summary.py
pacer_tools/code/support/__init__.py
pacer_tools/code/support/bundler.py
pacer_tools/code/support/core.py
pacer_tools/code/support/counsel_functions.py
pacer_tools/code/support/court_functions.py
pacer_tools/code/support/data_tools.py
pacer_tools/code/support/disambiguation_functions.py
pacer_tools/code/support/docket_entry_identification.py
pacer_tools/code/support/docket_functions.py
pacer_tools/code/support/fhandle_tools.py
pacer_tools/code/support/fjc.py
pacer_tools/code/support/judge_functions.py
pacer_tools/code/support/language_tools.py
pacer_tools/code/support/lexicon.py
pacer_tools/code/support/mongo_connector.py
pacer_tools/code/support/party_classification.py
pacer_tools/code/support/party_tagging.py
pacer_tools/code/support/research_tools.py
pacer_tools/code/support/scales_shell.py
pacer_tools/code/support/settings.py
pacer_tools/code/support/stats.py
pacer_tools/code/support/text_functions.py
pacer_tools/code/support/viz_tools.py
pacer_tools/code/support/core_data/brmag_judges.csv
pacer_tools/code/support/core_data/brmag_positions.csv
pacer_tools/code/support/core_data/district_courts.csv
pacer_tools/code/support/core_data/district_courts_94.csv
pacer_tools/code/support/core_data/judge_demographics.csv
pacer_tools/code/support/core_data/nature_suit.csv
pacer_tools/code/support/core_data/statey2code.json
pacer_tools/code/tasks/__init__.py
pacer_tools/code/tasks/build_unique_table.py
pacer_tools/code/tasks/redact_pacer.py
pacer_tools/data/annotation/district_courts.csv
pacer_tools/data/annotation/member_lead_links.csv
pacer_tools-0.1.11.dist-info/LICENSE
pacer_tools-0.1.11.dist-info/METADATA
pacer_tools-0.1.11.dist-info/WHEEL
pacer_tools-0.1.11.dist-info/entry_points.txt
pacer_tools-0.1.11.dist-info/top_level.txt
pacer_tools-0.1.11.dist-info/RECORD
